dynamodb_python/__init__.py
dynamodb_python/dynamodb.py
dynamodb_python/table.py
dynamodb_python/utils.py
dynamodb_python-0.1.4.dist-info/LICENSE
dynamodb_python-0.1.4.dist-info/METADATA
dynamodb_python-0.1.4.dist-info/WHEEL
dynamodb_python-0.1.4.dist-info/RECORD
