Metadata-Version: 2.1
Name: dynamodb-python
Version: 0.1.4
Summary: 
Author: domas-v
Author-email: domas.vaitmonas93@gmail.com
Requires-Python: >=3.9,<4.0
Classifier: Programming Language :: Python :: 3
Classifier: Programming Language :: Python :: 3.9
Classifier: Programming Language :: Python :: 3.10
Classifier: Programming Language :: Python :: 3.11
Classifier: Programming Language :: Python :: 3.12
Requires-Dist: boto3 (>=1.26.65,<2.0.0)
Requires-Dist: botocore (>=1.29.65,<2.0.0)
Requires-Dist: ddbcereal (>=2.1.1,<3.0.0)
Requires-Dist: requests (>=2.28.2,<3.0.0)
